plpipes/__init__.py
plpipes/autoaction.py
plpipes/config.py
plpipes/exceptions.py
plpipes/filesystem.py
plpipes/init.py
plpipes/jupyter.py
plpipes/plugin.py
plpipes/runner.py
plpipes/action/__init__.py
plpipes/action/base.py
plpipes/action/registry.py
plpipes/action/runner.py
plpipes/action/driver/__init__.py
plpipes/action/driver/archive_unpacker.py
plpipes/action/driver/file_downloader.py
plpipes/action/driver/loop.py
plpipes/action/driver/prql.py
plpipes/action/driver/quarto.py
plpipes/action/driver/simple.py
plpipes/action/driver/downloader/__init__.py
plpipes/action/driver/downloader/helpers.py
plpipes/action/driver/downloader/service/__init__.py
plpipes/action/driver/downloader/service/aemet.py
plpipes/action/driver/downloader/service/ine.py
plpipes/action/driver/sql/__init__.py
plpipes/action/driver/sql/jinja2.py
plpipes/cloud/__init__.py
plpipes/cloud/azure/__init__.py
plpipes/cloud/azure/graph.py
plpipes/cloud/azure/auth/__init__.py
plpipes/cloud/azure/auth/base.py
plpipes/cloud/azure/auth/plugin/__init__.py
plpipes/cloud/azure/auth/plugin/azure_cli.py
plpipes/cloud/azure/auth/plugin/client_secret.py
plpipes/cloud/azure/auth/plugin/interactive_browser.py
plpipes/cloud/azure/auth/plugin/managed_identity.py
plpipes/cloud/google/__init__.py
plpipes/cloud/google/vertexai.py
plpipes/cloud/google/auth/__init__.py
plpipes/cloud/google/auth/base.py
plpipes/cloud/google/auth/plugin/__init__.py
plpipes/cloud/google/auth/plugin/oauth2.py
plpipes/cloud/openai/__init__.py
plpipes/cloud/openai/provider/__init__.py
plpipes/cloud/openai/provider/plugin/__init__.py
plpipes/cloud/openai/provider/plugin/azure.py
plpipes/cloud/openai/provider/plugin/openai.py
plpipes/database/__init__.py
plpipes/database/sqlext.py
plpipes/database/backend/__init__.py
plpipes/database/backend/dict.py
plpipes/database/backend/geopandas.py
plpipes/database/backend/pandas.py
plpipes/database/backend/spark.py
plpipes/database/backend/tuple.py
plpipes/database/backend/plugin/__init__.py
plpipes-0.4.dist-info/licenses/LICENSE
plpipes-0.4.dist-info/WHEEL
plpipes-0.4.dist-info/METADATA
plpipes-0.4.dist-info/RECORD
