Metadata-Version: 2.4
Name: plpipes
Version: 0.4
Summary: PredictLand Data Science Framwork
Author-email: PredictLand <info@predictland.com>
Classifier: License :: OSI Approved :: MIT License
License-File: LICENSE
Requires-Dist: requests >=2.0
Requires-Dist: duckdb >=0.6
Requires-Dist: duckdb-engine >=0.6
Requires-Dist: numpy >=1.14
Requires-Dist: PyYAML >=6.0
Requires-Dist: Jinja2 >=3.1
Requires-Dist: pandas >=1.5
Requires-Dist: SQLAlchemy >=1.4
Requires-Dist: prql-python >=0.3
Requires-Dist: httpx >=0.23
Requires-Dist: sqlparse >= 0.5
Requires-Dist: friendlydateparser > 0.2.2
Requires-Dist: findapp >= 0.0.1
Requires-Dist: colorlog >= 6.9.0
Requires-Dist: azure-identity ; extra == "azure"
Requires-Dist: jupyterlab >=1.0 ; extra == "jupyter"
Requires-Dist: pyprql >=0.5 ; extra == "jupyter"
Requires-Dist: ipython-sql >=0.4 ; extra == "jupyter"
Requires-Dist: azure-identity ; extra == "msgraph"
Requires-Dist: ms-graph-client ; extra == "msgraph"
Requires-Dist: pyodbc >=4.0 ; extra == "odbc"
Project-URL: Home, https://github.com/PredictLand/PL-TEC-PLPipes
Provides-Extra: azure
Provides-Extra: jupyter
Provides-Extra: msgraph
Provides-Extra: odbc
